session_forge-0.1.0.dist-info/licenses/LICENSE
sf/__init__.py
sf/cli.py
sf/models.py
sf/core/git.py
sf/core/locks.py
sf/core/orchestrator.py
sf/core/ssh.py
sf/core/state.py
session_forge-0.1.0.dist-info/METADATA
session_forge-0.1.0.dist-info/WHEEL
session_forge-0.1.0.dist-info/entry_points.txt
session_forge-0.1.0.dist-info/top_level.txt
session_forge-0.1.0.dist-info/RECORD
