Metadata-Version: 2.4
Name: session-forge
Version: 0.1.0
Summary: Session Forge (sf): orchestrate remote worktrees and project setup for HAPI-managed sessions.
Author-email: Session Forge Maintainers <oss@session-forge.dev>
License: Apache-2.0
Keywords: cli,ssh,git,worktree,hapi
Classifier: Programming Language :: Python :: 3
Classifier: Programming Language :: Python :: 3.10
Classifier: License :: OSI Approved :: Apache Software License
Classifier: Operating System :: OS Independent
Requires-Python: >=3.10
License-File: LICENSE
Requires-Dist: typer>=0.12
Requires-Dist: rich>=13.7
Requires-Dist: PyYAML>=6.0
Requires-Dist: pydantic>=2.5
Provides-Extra: dev
Requires-Dist: pytest>=7.0; extra == "dev"
Requires-Dist: black>=24.0; extra == "dev"
Requires-Dist: isort>=5.12; extra == "dev"
Dynamic: license-file
